{
  "project_info": {
    "project_number": "905943965718",
    "project_id": "nammayantra-app",
    "storage_bucket": "nammayantra-app.firebasestorage.app"
  },
  "client": [
    {
      "client_info": {
        "mobilesdk_app_id": "1:905943965718:android:7b080afb16bfe2245e5537",
        "android_client_info": {
          "package_name": "com.nammayantra"
        }
      },
      "oauth_client": [],
      "api_key": [
        {
          "current_key": "AIzaSyAbuQLjTq2xXA9uyixcnC2-teiHDzqxWaw"
        }
      ],
      "services": {
        "appinvite_service": {
          "other_platform_oauth_client": []
        }
      }
    }
  ],
  "configuration_version": "1"
}
